{
    "basic_info": {
        "sectors": [
            "Digital Marketing"
        ],
        "company_name": "e intelligence",
        "logo_url": "https://img.shgstatic.com/clutch-static-prod/image/scale/50x50/s3fs-public/logos/573b6b52fb288c107e2035a5ff2dbe10.png",
        "company_tagline": "⭐️⭐️⭐️⭐⭐More Traffic, More Customers, More Revenue",
        "min_project_size": "$1,000+",
        "avg_hourly_rate": "$25 - $49",
        "employee_count": "10 - 49",
        "primary_location": "London, United Kingdom",
        "founded_date": "2005",
        "about_us": "e intelligence is a leading Digital Marketing and Web Development Agency that helps businesses build their brands across the globe. Our tailor-made digital solutions help companies increase revenue through our Digital Marketing, SEO, PPC and Website Development Services.Whether you’re small or large, we have just the right solution for your growth needs.Our ROI focused approach and a passionate team help us deliver our services that help our clients grow. A combination of intelligence and diligence is what sets us apart from the competition, worldwide. Leading brands rely on our expertise to help them growSo whatever your digital pursuit may be, we are all ears! Visitwww.eintelligenceweb.comRead more..."
    }
}